[{"選課代號": " 4739", "上課校區": " 第一校區", "部別": " 日間部四技", "科系": " 外語教育中心", "班級": " 外語四技一甲(第", "合班班級": " ", "永久課號": " 043C10229", "科目名稱": " 日語(二)", "學分": " 2.0", "授課時數": " 2.0", "實習時數": " 0", "必/選": " 選修", "授課教師": " 林秀芬", "教室": " E008", "修課人數": " 30", "人數上限": " 30", "上課時間": " (一)5-6", "全英語授課": " 否", "遠距教學": " 否", "授課大綱": "授課大綱", "備註": " 限非應日系學生修讀，107學年度後入學生通過英語免修計入外語畢業學分。"}, {"選課代號": " 4740", "上課校區": " 第一校區", "部別": " 日間部四技", "科系": " 外語教育中心", "班級": " 外語四技一甲(第", "合班班級": " ", "永久課號": " 043C10229", "科目名稱": " 日語(二)", "學分": " 2.0", "授課時數": " 2.0", "實習時數": " 0", "必/選": " 選修", "授課教師": " 謝宗倫", "教室": " E207", "修課人數": " 30", "人數上限": " 30", "上課時間": " (一)5-6", "全英語授課": " 否", "遠距教學": " 否", "授課大綱": "授課大綱", "備註": " 限非應日系學生修讀，107學年度後入學生通過英語免修計入外語畢業學分。"}, {"選課代號": " 4741", "上課校區": " 第一校區", "部別": " 日間部四技", "科系": " 外語教育中心", "班級": " 外語四技一甲(第", "合班班級": " ", "永久課號": " 043C10229", "科目名稱": " 日語(二)", "學分": " 2.0", "授課時數": " 2.0", "實習時數": " 0", "必/選": " 選修", "授課教師": " 洪瓔玲", "教室": " E003", "修課人數": " 26", "人數上限": " 30", "上課時間": " (一)5-6", "全英語授課": " 否", "遠距教學": " 否", "授課大綱": "授課大綱", "備註": " 限非應日系學生修讀，107學年度後入學生通過英語免修計入外語畢業學分。"}, {"選課代號": " 4742", "上課校區": " 第一校區", "部別": " 日間部四技", "科系": " 外語教育中心", "班級": " 外語四技一甲(第", "合班班級": " ", "永久課號": " 043C10229", "科目名稱": " 日語(二)", "學分": " 2.0", "授課時數": " 2.0", "實習時數": " 0", "必/選": " 選修", "授課教師": " 謝宗倫", "教室": " E207", "修課人數": " 30", "人數上限": " 30", "上課時間": " (一)7-8", "全英語授課": " 否", "遠距教學": " 否", "授課大綱": "授課大綱", "備註": " 限非應日系學生修讀，107學年度後入學生通過英語免修計入外語畢業學分。"}, {"選課代號": " 4743", "上課校區": " 第一校區", "部別": " 日間部四技", "科系": " 外語教育中心", "班級": " 外語四技一甲(第", "合班班級": " ", "永久課號": " 043C10229", "科目名稱": " 日語(二)", "學分": " 2.0", "授課時數": " 2.0", "實習時數": " 0", "必/選": " 選修", "授課教師": " 陳貌卿", "教室": " E302", "修課人數": " 30", "人數上限": " 30", "上課時間": " (五)3-4", "全英語授課": " 否", "遠距教學": " 否", "授課大綱": "授課大綱", "備註": " 限非應日系學生修讀，107學年度後入學生通過英語免修計入外語畢業學分。"}, {"選課代號": " 4744", "上課校區": " 第一校區", "部別": " 日間部四技", "科系": " 外語教育中心", "班級": " 外語四技一甲(第", "合班班級": " ", "永久課號": " 043C10229", "科目名稱": " 日語(二)", "學分": " 2.0", "授課時數": " 2.0", "實習時數": " 0", "必/選": " 選修", "授課教師": " 林秀芬", "教室": " D104", "修課人數": " 24", "人數上限": " 30", "上課時間": " (五)1-2", "全英語授課": " 否", "遠距教學": " 否", "授課大綱": "授課大綱", "備註": " 限非應日系學生修讀，107學年度後入學生通過英語免修計入外語畢業學分。"}, {"選課代號": " 4745", "上課校區": " 第一校區", "部別": " 日間部四技", "科系": " 外語教育中心", "班級": " 外語四技一甲(第", "合班班級": " ", "永久課號": " 043C10229", "科目名稱": " 日語(二)", "學分": " 2.0", "授課時數": " 2.0", "實習時數": " 0", "必/選": " 選修", "授課教師": " 斎藤雅子", "教室": " E420", "修課人數": " 13", "人數上限": " 30", "上課時間": " (五)1-2", "全英語授課": " 否", "遠距教學": " 否", "授課大綱": "授課大綱", "備註": " 限非應日系學生修讀，107學年度後入學生通過英語免修計入外語畢業學分。"}, {"選課代號": " 4746", "上課校區": " 第一校區", "部別": " 日間部四技", "科系": " 外語教育中心", "班級": " 外語四技一甲(第", "合班班級": " ", "永久課號": " 043C10229", "科目名稱": " 日語(二)", "學分": " 2.0", "授課時數": " 2.0", "實習時數": " 0", "必/選": " 選修", "授課教師": " 洪瓔玲", "教室": " E403", "修課人數": " 16", "人數上限": " 30", "上課時間": " (五)1-2", "全英語授課": " 否", "遠距教學": " 否", "授課大綱": "授課大綱", "備註": " 限非應日系學生修讀，107學年度後入學生通過英語免修計入外語畢業學分。"}, {"選課代號": " 4748", "上課校區": " 第一校區", "部別": " 日間部四技", "科系": " 外語教育中心", "班級": " 外語四技一甲(第", "合班班級": " ", "永久課號": " 043C10229", "科目名稱": " 日語(二)", "學分": " 2.0", "授課時數": " 2.0", "實習時數": " 0", "必/選": " 選修", "授課教師": " 黃惠玲", "教室": " C204", "修課人數": " 12", "人數上限": " 30", "上課時間": " (五)3-4", "全英語授課": " 否", "遠距教學": " 否", "授課大綱": "授課大綱", "備註": " 限非應日系學生修讀，107學年度後入學生通過英語免修計入外語畢業學分。"}, {"選課代號": " 4749", "上課校區": " 第一校區", "部別": " 日間部四技", "科系": " 外語教育中心", "班級": " 外語四技一甲(第", "合班班級": " ", "永久課號": " 043C10229", "科目名稱": " 日語(二)", "學分": " 2.0", "授課時數": " 2.0", "實習時數": " 0", "必/選": " 選修", "授課教師": " 斎藤雅子", "教室": " E420", "修課人數": " 27", "人數上限": " 30", "上課時間": " (五)3-4", "全英語授課": " 否", "遠距教學": " 否", "授課大綱": "授課大綱", "備註": " 限非應日系學生修讀，107學年度後入學生通過英語免修計入外語畢業學分。"}, {"選課代號": " 4750", "上課校區": " 第一校區", "部別": " 日間部四技", "科系": " 外語教育中心", "班級": " 外語四技一甲(第", "合班班級": " ", "永久課號": " 043C10229", "科目名稱": " 日語(二)", "學分": " 2.0", "授課時數": " 2.0", "實習時數": " 0", "必/選": " 選修", "授課教師": " 洪瓔玲", "教室": " E403", "修課人數": " 30", "人數上限": " 30", "上課時間": " (五)3-4", "全英語授課": " 否", "遠距教學": " 否", "授課大綱": "授課大綱", "備註": " 限非應日系學生修讀，107學年度後入學生通過英語免修計入外語畢業學分。"}, {"選課代號": " 4751", "上課校區": " 第一校區", "部別": " 日間部四技", "科系": " 外語教育中心", "班級": " 外語四技一甲(第", "合班班級": " ", "永久課號": " 043C00005", "科目名稱": " 實用英文(二)", "學分": " 2.0", "授課時數": " 2.0", "實習時數": " 0", "必/選": " 必修", "授課教師": " 葉采旻", "教室": " B222", "修課人數": " 29", "人數上限": " 0", "上課時間": " (一)5-6", "全英語授課": " 否", "遠距教學": " 否", "授課大綱": "授課大綱", "備註": " 不開放選課：由外語中心依級數分班【限工.電資院選修：初-1】"}, {"選課代號": " 4752", "上課校區": " 第一校區", "部別": " 日間部四技", "科系": " 外語教育中心", "班級": " 外語四技一甲(第", "合班班級": " ", "永久課號": " 043C00005", "科目名稱": " 實用英文(二)", "學分": " 2.0", "授課時數": " 2.0", "實習時數": " 0", "必/選": " 必修", "授課教師": " 葉采旻", "教室": " B222", "修課人數": " 28", "人數上限": " 0", "上課時間": " (一)7-8", "全英語授課": " 否", "遠距教學": " 否", "授課大綱": "授課大綱", "備註": " 不開放選課：由外語中心依級數分班【限工.電資院選修：初-2】"}, {"選課代號": " 4753", "上課校區": " 第一校區", "部別": " 日間部四技", "科系": " 外語教育中心", "班級": " 外語四技一甲(第", "合班班級": " ", "永久課號": " 043C00005", "科目名稱": " 實用英文(二)", "學分": " 2.0", "授課時數": " 2.0", "實習時數": " 0", "必/選": " 必修", "授課教師": " 羅麗卿", "教室": " E306", "修課人數": " 36", "人數上限": " 0", "上課時間": " (一)5-6", "全英語授課": " 否", "遠距教學": " 否", "授課大綱": "授課大綱", "備註": " 不開放選課：由外語中心依級數分班【限工.電資院選修：中-3】"}, {"選課代號": " 4754", "上課校區": " 第一校區", "部別": " 日間部四技", "科系": " 外語教育中心", "班級": " 外語四技一甲(第", "合班班級": " ", "永久課號": " 043C00005", "科目名稱": " 實用英文(二)", "學分": " 2.0", "授課時數": " 2.0", "實習時數": " 0", "必/選": " 必修", "授課教師": " 謝雅菁", "教室": " E206", "修課人數": " 36", "人數上限": " 0", "上課時間": " (一)5-6", "全英語授課": " 否", "遠距教學": " 否", "授課大綱": "授課大綱", "備註": " 不開放選課：由外語中心依級數分班【限工.電資院選修：中-4】"}, {"選課代號": " 4755", "上課校區": " 第一校區", "部別": " 日間部四技", "科系": " 外語教育中心", "班級": " 外語四技一甲(第", "合班班級": " ", "永久課號": " 043C00005", "科目名稱": " 實用英文(二)", "學分": " 2.0", "授課時數": " 2.0", "實習時數": " 0", "必/選": " 必修", "授課教師": " 張晴", "教室": " J124", "修課人數": " 37", "人數上限": " 0", "上課時間": " (一)5-6", "全英語授課": " 否", "遠距教學": " 否", "授課大綱": "授課大綱", "備註": " 不開放選課：由外語中心依級數分班【限工.電資院選修：中-5】"}, {"選課代號": " 4756", "上課校區": " 第一校區", "部別": " 日間部四技", "科系": " 外語教育中心", "班級": " 外語四技一甲(第", "合班班級": " ", "永久課號": " 043C00005", "科目名稱": " 實用英文(二)", "學分": " 2.0", "授課時數": " 2.0", "實習時數": " 0", "必/選": " 必修", "授課教師": " 鄭雅尹", "教室": " D009", "修課人數": " 38", "人數上限": " 0", "上課時間": " (一)5-6", "全英語授課": " 否", "遠距教學": " 否", "授課大綱": "授課大綱", "備註": " 不開放選課：由外語中心依級數分班【限工.電資院選修：中-6】"}, {"選課代號": " 4757", "上課校區": " 第一校區", "部別": " 日間部四技", "科系": " 外語教育中心", "班級": " 外語四技一甲(第", "合班班級": " ", "永久課號": " 043C00005", "科目名稱": " 實用英文(二)", "學分": " 2.0", "授課時數": " 2.0", "實習時數": " 0", "必/選": " 必修", "授課教師": " 牛亞琪", "教室": " E001", "修課人數": " 38", "人數上限": " 0", "上課時間": " (一)5-6", "全英語授課": " 否", "遠距教學": " 否", "授課大綱": "授課大綱", "備註": " 不開放選課：由外語中心依級數分班【限工.電資院選修：中-7】"}, {"選課代號": " 4758", "上課校區": " 第一校區", "部別": " 日間部四技", "科系": " 外語教育中心", "班級": " 外語四技一甲(第", "合班班級": " ", "永久課號": " 043C00005", "科目名稱": " 實用英文(二)", "學分": " 2.0", "授課時數": " 2.0", "實習時數": " 0", "必/選": " 必修", "授課教師": " 謝雅菁", "教室": " E206", "修課人數": " 35", "人數上限": " 0", "上課時間": " (一)7-8", "全英語授課": " 否", "遠距教學": " 否", "授課大綱": "授課大綱", "備註": " 不開放選課：由外語中心依級數分班【限工.電資院選修：中-8】"}, {"選課代號": " 4759", "上課校區": " 第一校區", "部別": " 日間部四技", "科系": " 外語教育中心", "班級": " 外語四技一甲(第", "合班班級": " ", "永久課號": " 043C00005", "科目名稱": " 實用英文(二)", "學分": " 2.0", "授課時數": " 2.0", "實習時數": " 0", "必/選": " 必修", "授課教師": " 羅麗卿", "教室": " E306", "修課人數": " 36", "人數上限": " 0", "上課時間": " (一)7-8", "全英語授課": " 否", "遠距教學": " 否", "授課大綱": "授課大綱", "備註": " 不開放選課：由外語中心依級數分班【限工.電資院選修：中-9】"}, {"選課代號": " 4760", "上課校區": " 第一校區", "部別": " 日間部四技", "科系": " 外語教育中心", "班級": " 外語四技一甲(第", "合班班級": " ", "永久課號": " 043C00005", "科目名稱": " 實用英文(二)", "學分": " 2.0", "授課時數": " 2.0", "實習時數": " 0", "必/選": " 必修", "授課教師": " 陳佳艷", "教室": " E008", "修課人數": " 34", "人數上限": " 0", "上課時間": " (一)7-8", "全英語授課": " 否", "遠距教學": " 否", "授課大綱": "授課大綱", "備註": " 不開放選課：由外語中心依級數分班【限工.電資院選修：中-10】"}, {"選課代號": " 4761", "上課校區": " 第一校區", "部別": " 日間部四技", "科系": " 外語教育中心", "班級": " 外語四技一甲(第", "合班班級": " ", "永久課號": " 043C00005", "科目名稱": " 實用英文(二)", "學分": " 2.0", "授課時數": " 2.0", "實習時數": " 0", "必/選": " 必修", "授課教師": " 鄭雅尹", "教室": " D009", "修課人數": " 37", "人數上限": " 0", "上課時間": " (一)7-8", "全英語授課": " 否", "遠距教學": " 否", "授課大綱": "授課大綱", "備註": " 不開放選課：由外語中心依級數分班【限工.電資院選修：中-11】"}, {"選課代號": " 4762", "上課校區": " 第一校區", "部別": " 日間部四技", "科系": " 外語教育中心", "班級": " 外語四技一甲(第", "合班班級": " ", "永久課號": " 043C00005", "科目名稱": " 實用英文(二)", "學分": " 2.0", "授課時數": " 2.0", "實習時數": " 0", "必/選": " 必修", "授課教師": " 牛亞琪", "教室": " E001", "修課人數": " 37", "人數上限": " 0", "上課時間": " (一)7-8", "全英語授課": " 否", "遠距教學": " 否", "授課大綱": "授課大綱", "備註": " 不開放選課：由外語中心依級數分班【限工.電資院選修：中-12】"}, {"選課代號": " 4763", "上課校區": " 第一校區", "部別": " 日間部四技", "科系": " 外語教育中心", "班級": " 外語四技一甲(第", "合班班級": " ", "永久課號": " 043C00005", "科目名稱": " 實用英文(二)", "學分": " 2.0", "授課時數": " 2.0", "實習時數": " 0", "必/選": " 必修", "授課教師": " 侯仰霞", "教室": " E205", "修課人數": " 35", "人數上限": " 0", "上課時間": " (一)7-8", "全英語授課": " 否", "遠距教學": " 否", "授課大綱": "授課大綱", "備註": " 不開放選課：由外語中心依級數分班【限工.電資院選修：高-13】"}, {"選課代號": " 4764", "上課校區": " 第一校區", "部別": " 日間部四技", "科系": " 外語教育中心", "班級": " 外語四技一甲(第", "合班班級": " ", "永久課號": " 043C00005", "科目名稱": " 實用英文(二)", "學分": " 2.0", "授課時數": " 2.0", "實習時數": " 0", "必/選": " 必修", "授課教師": " 胡智翔", "教室": " E214", "修課人數": " 33", "人數上限": " 0", "上課時間": " (一)5-6", "全英語授課": " 否", "遠距教學": " 否", "授課大綱": "授課大綱", "備註": " 不開放選課：由外語中心依級數分班【限工.電資院選修：高-14】"}, {"選課代號": " 4765", "上課校區": " 第一校區", "部別": " 日間部四技", "科系": " 外語教育中心", "班級": " 外語四技一甲(第", "合班班級": " ", "永久課號": " 043C00005", "科目名稱": " 實用英文(二)", "學分": " 2.0", "授課時數": " 2.0", "實習時數": " 0", "必/選": " 必修", "授課教師": " 施茹譯", "教室": " E204", "修課人數": " 35", "人數上限": " 0", "上課時間": " (一)7-8", "全英語授課": " 否", "遠距教學": " 否", "授課大綱": "授課大綱", "備註": " 不開放選課：由外語中心依級數分班【限工.電資院選修：高-15】"}, {"選課代號": " 4766", "上課校區": " 第一校區", "部別": " 日間部四技", "科系": " 外語教育中心", "班級": " 外語四技一甲(第", "合班班級": " ", "永久課號": " 043C00005", "科目名稱": " 實用英文(二)", "學分": " 2.0", "授課時數": " 2.0", "實習時數": " 0", "必/選": " 必修", "授課教師": " 胡智翔", "教室": " E214", "修課人數": " 33", "人數上限": " 0", "上課時間": " (一)7-8", "全英語授課": " 否", "遠距教學": " 否", "授課大綱": "授課大綱", "備註": " 不開放選課：由外語中心依級數分班【限工.電資院選修：高-16】"}, {"選課代號": " 4767", "上課校區": " 第一校區", "部別": " 日間部四技", "科系": " 外語教育中心", "班級": " 外語四技一甲(第", "合班班級": " ", "永久課號": " 043C00005", "科目名稱": " 實用英文(二)", "學分": " 2.0", "授課時數": " 2.0", "實習時數": " 0", "必/選": " 必修", "授課教師": " 林子宸", "教室": " E110", "修課人數": " 40", "人數上限": " 0", "上課時間": " (一)5-6", "全英語授課": " 否", "遠距教學": " 否", "授課大綱": "授課大綱", "備註": " 不開放選課：由外語中心依級數分班【限工.電資院選修：高-17】"}, {"選課代號": " 4768", "上課校區": " 第一校區", "部別": " 日間部四技", "科系": " 外語教育中心", "班級": " 外語四技一甲(第", "合班班級": " ", "永久課號": " 043C00005", "科目名稱": " 實用英文(二)", "學分": " 2.0", "授課時數": " 2.0", "實習時數": " 0", "必/選": " 必修", "授課教師": " 林子宸", "教室": " E110", "修課人數": " 37", "人數上限": " 0", "上課時間": " (一)7-8", "全英語授課": " 否", "遠距教學": " 否", "授課大綱": "授課大綱", "備註": " 不開放選課：由外語中心依級數分班【限工.電資院選修：高-18】"}, {"選課代號": " 4769", "上課校區": " 第一校區", "部別": " 日間部四技", "科系": " 外語教育中心", "班級": " 外語四技一甲(第", "合班班級": " ", "永久課號": " 043C00005", "科目名稱": " 實用英文(二)", "學分": " 2.0", "授課時數": " 2.0", "實習時數": " 0", "必/選": " 必修", "授課教師": " 趙秀玲", "教室": " E306", "修課人數": " 35", "人數上限": " 0", "上課時間": " (五)3-4", "全英語授課": " 否", "遠距教學": " 否", "授課大綱": "授課大綱", "備註": " 不開放選課：由外語中心依級數分班【限外.財.管院選修：高-19】"}, {"選課代號": " 4770", "上課校區": " 第一校區", "部別": " 日間部四技", "科系": " 外語教育中心", "班級": " 外語四技一甲(第", "合班班級": " ", "永久課號": " 043C00005", "科目名稱": " 實用英文(二)", "學分": " 2.0", "授課時數": " 2.0", "實習時數": " 0", "必/選": " 必修", "授課教師": " 孫英敏", "教室": " E011", "修課人數": " 27", "人數上限": " 0", "上課時間": " (五)1-2", "全英語授課": " 否", "遠距教學": " 否", "授課大綱": "授課大綱", "備註": " 不開放選課：由外語中心依級數分班【限外.財.管院選修：初-20】"}, {"選課代號": " 4771", "上課校區": " 第一校區", "部別": " 日間部四技", "科系": " 外語教育中心", "班級": " 外語四技一甲(第", "合班班級": " ", "永久課號": " 043C00005", "科目名稱": " 實用英文(二)", "學分": " 2.0", "授課時數": " 2.0", "實習時數": " 0", "必/選": " 必修", "授課教師": " 孫婉鈞", "教室": " E422", "修課人數": " 27", "人數上限": " 0", "上課時間": " (五)1-2", "全英語授課": " 否", "遠距教學": " 否", "授課大綱": "授課大綱", "備註": " 不開放選課：由外語中心依級數分班【限外.財.管院選修：中-21】"}, {"選課代號": " 4772", "上課校區": " 第一校區", "部別": " 日間部四技", "科系": " 外語教育中心", "班級": " 外語四技一甲(第", "合班班級": " ", "永久課號": " 043C00005", "科目名稱": " 實用英文(二)", "學分": " 2.0", "授課時數": " 2.0", "實習時數": " 0", "必/選": " 必修", "授課教師": " 孫婉鈞", "教室": " E422", "修課人數": " 30", "人數上限": " 0", "上課時間": " (五)3-4", "全英語授課": " 否", "遠距教學": " 否", "授課大綱": "授課大綱", "備註": " 不開放選課：由外語中心依級數分班【限外.財.管院選修：中-22】"}, {"選課代號": " 4773", "上課校區": " 第一校區", "部別": " 日間部四技", "科系": " 外語教育中心", "班級": " 外語四技一甲(第", "合班班級": " ", "永久課號": " 043C00005", "科目名稱": " 實用英文(二)", "學分": " 2.0", "授課時數": " 2.0", "實習時數": " 0", "必/選": " 必修", "授課教師": " 張孟文", "教室": " E002", "修課人數": " 28", "人數上限": " 0", "上課時間": " (五)1-2", "全英語授課": " 否", "遠距教學": " 否", "授課大綱": "授課大綱", "備註": " 不開放選課：由外語中心依級數分班【限外.財.管院選修：中-23】"}, {"選課代號": " 4774", "上課校區": " 第一校區", "部別": " 日間部四技", "科系": " 外語教育中心", "班級": " 外語四技一甲(第", "合班班級": " ", "永久課號": " 043C00005", "科目名稱": " 實用英文(二)", "學分": " 2.0", "授課時數": " 2.0", "實習時數": " 0", "必/選": " 必修", "授課教師": " 蔣興華", "教室": " D308", "修課人數": " 29", "人數上限": " 0", "上課時間": " (五)1-2", "全英語授課": " 否", "遠距教學": " 否", "授課大綱": "授課大綱", "備註": " 不開放選課：由外語中心依級數分班【限外.財.管院選修：中-24】"}, {"選課代號": " 4775", "上課校區": " 第一校區", "部別": " 日間部四技", "科系": " 外語教育中心", "班級": " 外語四技一甲(第", "合班班級": " ", "永久課號": " 043C00005", "科目名稱": " 實用英文(二)", "學分": " 2.0", "授課時數": " 2.0", "實習時數": " 0", "必/選": " 必修", "授課教師": " 牛亞琪", "教室": " D107", "修課人數": " 29", "人數上限": " 0", "上課時間": " (五)1-2", "全英語授課": " 否", "遠距教學": " 否", "授課大綱": "授課大綱", "備註": " 不開放選課：由外語中心依級數分班【限外.財.管院選修：中-25】"}, {"選課代號": " 4776", "上課校區": " 第一校區", "部別": " 日間部四技", "科系": " 外語教育中心", "班級": " 外語四技一甲(第", "合班班級": " ", "永久課號": " 043C00005", "科目名稱": " 實用英文(二)", "學分": " 2.0", "授課時數": " 2.0", "實習時數": " 0", "必/選": " 必修", "授課教師": " 莊心瑜", "教室": " E209", "修課人數": " 31", "人數上限": " 0", "上課時間": "  (五)3-4", "全英語授課": " 否", "遠距教學": " 否", "授課大綱": "授課大綱", "備註": " 不開放選課：由外語中心依級數分班【限外.財.管院選修：中-26】"}, {"選課代號": " 4777", "上課校區": " 第一校區", "部別": " 日間部四技", "科系": " 外語教育中心", "班級": " 外語四技一甲(第", "合班班級": " ", "永久課號": " 043C00005", "科目名稱": " 實用英文(二)", "學分": " 2.0", "授課時數": " 2.0", "實習時數": " 0", "必/選": " 必修", "授課教師": " 張孟文", "教室": " E002", "修課人數": " 33", "人數上限": " 0", "上課時間": " (五)3-4", "全英語授課": " 否", "遠距教學": " 否", "授課大綱": "授課大綱", "備註": " 不開放選課：由外語中心依級數分班【限外.財.管院選修：中-27】"}, {"選課代號": " 4778", "上課校區": " 第一校區", "部別": " 日間部四技", "科系": " 外語教育中心", "班級": " 外語四技一甲(第", "合班班級": " ", "永久課號": " 043C00005", "科目名稱": " 實用英文(二)", "學分": " 2.0", "授課時數": " 2.0", "實習時數": " 0", "必/選": " 必修", "授課教師": " 楊千禛", "教室": " D107", "修課人數": " 31", "人數上限": " 0", "上課時間": " (五)3-4", "全英語授課": " 否", "遠距教學": " 否", "授課大綱": "授課大綱", "備註": " 不開放選課：由外語中心依級數分班【限外.財.管院選修：中-28】"}, {"選課代號": " 4779", "上課校區": " 第一校區", "部別": " 日間部四技", "科系": " 外語教育中心", "班級": " 外語四技一甲(第", "合班班級": " ", "永久課號": " 043C00005", "科目名稱": " 實用英文(二)", "學分": " 2.0", "授課時數": " 2.0", "實習時數": " 0", "必/選": " 必修", "授課教師": " 蔣興華", "教室": " D308", "修課人數": " 32", "人數上限": " 0", "上課時間": " (五)3-4", "全英語授課": " 否", "遠距教學": " 否", "授課大綱": "授課大綱", "備註": " 不開放選課：由外語中心依級數分班【限外.財.管院選修：中-29】"}, {"選課代號": " 4780", "上課校區": " 第一校區", "部別": " 日間部四技", "科系": " 外語教育中心", "班級": " 外語四技一甲(第", "合班班級": " ", "永久課號": " 043C00005", "科目名稱": " 實用英文(二)", "學分": " 2.0", "授課時數": " 2.0", "實習時數": " 0", "必/選": " 必修", "授課教師": " 呂欽鈺", "教室": " E423", "修課人數": " 34", "人數上限": " 0", "上課時間": " (五)1-2", "全英語授課": " 否", "遠距教學": " 否", "授課大綱": "授課大綱", "備註": " 不開放選課：由外語中心依級數分班【限外.財.管院選修：高-30】"}, {"選課代號": " 4781", "上課校區": " 第一校區", "部別": " 日間部四技", "科系": " 外語教育中心", "班級": " 外語四技一甲(第", "合班班級": " ", "永久課號": " 043C00005", "科目名稱": " 實用英文(二)", "學分": " 2.0", "授課時數": " 2.0", "實習時數": " 0", "必/選": " 必修", "授課教師": " 高玉珮", "教室": " D203", "修課人數": " 32", "人數上限": " 0", "上課時間": " (五)1-2", "全英語授課": " 否", "遠距教學": " 否", "授課大綱": "授課大綱", "備註": " 不開放選課：由外語中心依級數分班【限外.財.管院選修：高-31】"}, {"選課代號": " 4782", "上課校區": " 第一校區", "部別": " 日間部四技", "科系": " 外語教育中心", "班級": " 外語四技一甲(第", "合班班級": " ", "永久課號": " 043C00005", "科目名稱": " 實用英文(二)", "學分": " 2.0", "授課時數": " 2.0", "實習時數": " 0", "必/選": " 必修", "授課教師": " 吳書萱", "教室": " E419", "修課人數": " 34", "人數上限": " 0", "上課時間": " (五)1-2", "全英語授課": " 否", "遠距教學": " 否", "授課大綱": "授課大綱", "備註": " 不開放選課：由外語中心依級數分班【限外.財.管院選修：高-32】"}, {"選課代號": " 4783", "上課校區": " 第一校區", "部別": " 日間部四技", "科系": " 外語教育中心", "班級": " 外語四技一甲(第", "合班班級": " ", "永久課號": " 043C00005", "科目名稱": " 實用英文(二)", "學分": " 2.0", "授課時數": " 2.0", "實習時數": " 0", "必/選": " 必修", "授課教師": " 陳振剛", "教室": " E304", "修課人數": " 31", "人數上限": " 0", "上課時間": " (五)1-2", "全英語授課": " 否", "遠距教學": " 否", "授課大綱": "授課大綱", "備註": " 不開放選課：由外語中心依級數分班【限外.財.管院選修：高-33】"}, {"選課代號": " 4784", "上課校區": " 第一校區", "部別": " 日間部四技", "科系": " 外語教育中心", "班級": " 外語四技一甲(第", "合班班級": " ", "永久課號": " 043C00005", "科目名稱": " 實用英文(二)", "學分": " 2.0", "授課時數": " 2.0", "實習時數": " 0", "必/選": " 必修", "授課教師": " 林子宸", "教室": " E424", "修課人數": " 36", "人數上限": " 0", "上課時間": " (五)1-2", "全英語授課": " 否", "遠距教學": " 否", "授課大綱": "授課大綱", "備註": " 不開放選課：由外語中心依級數分班【限外.財.管院選修：高-34】"}, {"選課代號": " 4785", "上課校區": " 第一校區", "部別": " 日間部四技", "科系": " 外語教育中心", "班級": " 外語四技一甲(第", "合班班級": " ", "永久課號": " 043C00005", "科目名稱": " 實用英文(二)", "學分": " 2.0", "授課時數": " 2.0", "實習時數": " 0", "必/選": " 必修", "授課教師": " 呂欽鈺", "教室": " E423", "修課人數": " 35", "人數上限": " 0", "上課時間": " (五)3-4", "全英語授課": " 否", "遠距教學": " 否", "授課大綱": "授課大綱", "備註": " 不開放選課：由外語中心依級數分班【限外.財.管院選修：高-35】"}, {"選課代號": " 4786", "上課校區": " 第一校區", "部別": " 日間部四技", "科系": " 外語教育中心", "班級": " 外語四技一甲(第", "合班班級": " ", "永久課號": " 043C00005", "科目名稱": " 實用英文(二)", "學分": " 2.0", "授課時數": " 2.0", "實習時數": " 0", "必/選": " 必修", "授課教師": " 吳書萱", "教室": " E419", "修課人數": " 37", "人數上限": " 0", "上課時間": " (五)3-4", "全英語授課": " 否", "遠距教學": " 否", "授課大綱": "授課大綱", "備註": " 不開放選課：由外語中心依級數分班【限外.財.管院選修：高-36】"}, {"選課代號": " 4787", "上課校區": " 第一校區", "部別": " 日間部四技", "科系": " 外語教育中心", "班級": " 外語四技一甲(第", "合班班級": " ", "永久課號": " 043C00005", "科目名稱": " 實用英文(二)", "學分": " 2.0", "授課時數": " 2.0", "實習時數": " 0", "必/選": " 必修", "授課教師": " 高玉珮", "教室": " D203", "修課人數": " 36", "人數上限": " 0", "上課時間": " (五)3-4", "全英語授課": " 否", "遠距教學": " 否", "授課大綱": "授課大綱", "備註": " 不開放選課：由外語中心依級數分班【限外.財.管院選修：高-37】"}, {"選課代號": " 4788", "上課校區": " 第一校區", "部別": " 日間部四技", "科系": " 外語教育中心", "班級": " 外語四技一甲(第", "合班班級": " ", "永久課號": " 043C00005", "科目名稱": " 實用英文(二)", "學分": " 2.0", "授課時數": " 2.0", "實習時數": " 0", "必/選": " 必修", "授課教師": " 陳振剛", "教室": " E304", "修課人數": " 38", "人數上限": " 0", "上課時間": " (五)3-4", "全英語授課": " 否", "遠距教學": " 否", "授課大綱": "授課大綱", "備註": " 不開放選課：由外語中心依級數分班【限外.財.管院選修：高-38】"}, {"選課代號": " 4789", "上課校區": " 第一校區", "部別": " 日間部四技", "科系": " 外語教育中心", "班級": " 外語四技一甲(第", "合班班級": " ", "永久課號": " 043C10082", "科目名稱": " 觀光英語", "學分": " 2.0", "授課時數": " 2.0", "實習時數": " 0", "必/選": " 選修", "授課教師": " 莊心瑜", "教室": " E214", "修課人數": " 22", "人數上限": " 25", "上課時間": " (四)3-4", "全英語授課": " 是", "遠距教學": " 否", "授課大綱": "授課大綱", "備註": " 限非應英系學生修讀，107學年度後入學生通過英語免修計入外語畢業學分。"}, {"選課代號": " 4790", "上課校區": " 第一校區", "部別": " 日間部四技", "科系": " 外語教育中心", "班級": " 外語四技一甲(第", "合班班級": " ", "永久課號": " 043C10223", "科目名稱": " 德語(二)", "學分": " 2.0", "授課時數": " 2.0", "實習時數": " 0", "必/選": " 選修", "授課教師": " 翁幸瑜", "教室": " D103多功能教室", "修課人數": " 21", "人數上限": " 30", "上課時間": " (五)3-4", "全英語授課": " 否", "遠距教學": " 否", "授課大綱": "授課大綱", "備註": " 限非應德系學生修讀，107學年度後入學生通過英語免修計入外語畢業學分。"}, {"選課代號": " 4791", "上課校區": " 第一校區", "部別": " 日間部四技", "科系": " 外語教育中心", "班級": " 外語四技一甲(第", "合班班級": " ", "永久課號": " 043C10223", "科目名稱": " 德語(二)", "學分": " 2.0", "授課時數": " 2.0", "實習時數": " 0", "必/選": " 選修", "授課教師": " 黃靖時", "教室": " D301文化教室", "修課人數": " 23", "人數上限": " 30", "上課時間": " (五)3-4", "全英語授課": " 否", "遠距教學": " 否", "授課大綱": "授課大綱", "備註": " 限非應德系學生修讀，107學年度後入學生通過英語免修計入外語畢業學分。"}, {"選課代號": " 4792", "上課校區": " 第一校區", "部別": " 日間部四技", "科系": " 外語教育中心", "班級": " 外語四技一甲(第", "合班班級": " ", "永久課號": " 043C10223", "科目名稱": " 德語(二)", "學分": " 2.0", "授課時數": " 2.0", "實習時數": " 0", "必/選": " 選修", "授課教師": " 廖玉儀", "教室": " E305", "修課人數": " 17", "人數上限": " 30", "上課時間": " (五)1-2", "全英語授課": " 否", "遠距教學": " 否", "授課大綱": "授課大綱", "備註": " 限非應德系學生修讀，107學年度後入學生通過英語免修計入外語畢業學分。"}, {"選課代號": " 4793", "上課校區": " 第一校區", "部別": " 日間部四技", "科系": " 外語教育中心", "班級": " 外語四技一甲(第", "合班班級": " ", "永久課號": " 043C10223", "科目名稱": " 德語(二)", "學分": " 2.0", "授課時數": " 2.0", "實習時數": " 0", "必/選": " 選修", "授課教師": " 劉懿德", "教室": " E213", "修課人數": " 14", "人數上限": " 30", "上課時間": " (一)7-8", "全英語授課": " 否", "遠距教學": " 否", "授課大綱": "授課大綱", "備註": " 限非應德系學生修讀，107學年度後入學生通過英語免修計入外語畢業學分。"}, {"選課代號": " 4794", "上課校區": " 第一校區", "部別": " 日間部四技", "科系": " 外語教育中心", "班級": " 外語四技一甲(第", "合班班級": " ", "永久課號": " 043C10223", "科目名稱": " 德語(二)", "學分": " 2.0", "授課時數": " 2.0", "實習時數": " 0", "必/選": " 選修", "授課教師": " 李林坡", "教室": " E205", "修課人數": " 20", "人數上限": " 30", "上課時間": " (一)5-6", "全英語授課": " 否", "遠距教學": " 否", "授課大綱": "授課大綱", "備註": " 限非應德系學生修讀，107學年度後入學生通過英語免修計入外語畢業學分。"}, {"選課代號": " 4795", "上課校區": " 第一校區", "部別": " 日間部四技", "科系": " 外語教育中心", "班級": " 外語四技一甲(第", "合班班級": " ", "永久課號": " 043C10225", "科目名稱": " 德語(四)", "學分": " 2.0", "授課時數": " 2.0", "實習時數": " 0", "必/選": " 選修", "授課教師": " 廖玉儀", "教室": " E305", "修課人數": " 14", "人數上限": " 35", "上課時間": " (五)3-4", "全英語授課": " 否", "遠距教學": " 否", "授課大綱": "授課大綱", "備註": " 限非應德系學生修讀，107學年度後入學生通過英語免修計入外語畢業學分。"}, {"選課代號": " 4796", "上課校區": " 第一校區", "部別": " 日間部四技", "科系": " 外語教育中心", "班級": " 外語四技一甲(第", "合班班級": " ", "永久課號": " 043C10231", "科目名稱": " 日語(四)", "學分": " 2.0", "授課時數": " 2.0", "實習時數": " 0", "必/選": " 選修", "授課教師": " 吳純姍", "教室": " E012", "修課人數": " 26", "人數上限": " 35", "上課時間": " (一)5-6", "全英語授課": " 否", "遠距教學": " 否", "授課大綱": "授課大綱", "備註": " 限非應日系學生修讀，107學年度後入學生通過英語免修計入外語畢業學分。"}, {"選課代號": " 4798", "上課校區": " 第一校區", "部別": " 日間部四技", "科系": " 外語教育中心", "班級": " 外語四技一甲(第", "合班班級": " ", "永久課號": " 043C10231", "科目名稱": " 日語(四)", "學分": " 2.0", "授課時數": " 2.0", "實習時數": " 0", "必/選": " 選修", "授課教師": " 陳惠文", "教室": " D108", "修課人數": " 17", "人數上限": " 35", "上課時間": " (五)3-4", "全英語授課": " 否", "遠距教學": " 否", "授課大綱": "授課大綱", "備註": " 限非應日系學生修讀，107學年度後入學生通過英語免修計入外語畢業學分。"}, {"選課代號": " 4799", "上課校區": " 第一校區", "部別": " 日間部四技", "科系": " 外語教育中心", "班級": " 外語四技一甲(第", "合班班級": " ", "永久課號": " 043C10231", "科目名稱": " 日語(四)", "學分": " 2.0", "授課時數": " 2.0", "實習時數": " 0", "必/選": " 選修", "授課教師": " 林秀芬", "教室": " D104", "修課人數": " 35", "人數上限": " 35", "上課時間": " (五)3-4", "全英語授課": " 否", "遠距教學": " 否", "授課大綱": "授課大綱", "備註": " 限非應日系學生修讀，107學年度後入學生通過英語免修計入外語畢業學分。"}, {"選課代號": " 4800", "上課校區": " 第一校區", "部別": " 日間部四技", "科系": " 外語教育中心", "班級": " 外語四技一甲(第", "合班班級": " ", "永久課號": " 043C10233", "科目名稱": " 日語(六)", "學分": " 2.0", "授課時數": " 2.0", "實習時數": " 0", "必/選": " 選修", "授課教師": " 吳純姍", "教室": " E012", "修課人數": " 24", "人數上限": " 35", "上課時間": " (五)1-2", "全英語授課": " 否", "遠距教學": " 否", "授課大綱": "授課大綱", "備註": " 限非應日系學生修讀，107學年度後入學生通過英語免修計入外語畢業學分。"}, {"選課代號": " 4801", "上課校區": " 第一校區", "部別": " 日間部四技", "科系": " 外語教育中心", "班級": " 外語四技一甲(第", "合班班級": " ", "永久課號": " 043C10235", "科目名稱": " 日語(八)", "學分": " 2.0", "授課時數": " 2.0", "實習時數": " 0", "必/選": " 選修", "授課教師": " 吳純姍", "教室": " E012", "修課人數": " 14", "人數上限": " 35", "上課時間": " (五)3-4", "全英語授課": " 否", "遠距教學": " 否", "授課大綱": "授課大綱", "備註": " 限非應日系學生修讀，107學年度後入學生通過英語免修計入外語畢業學分。"}, {"選課代號": " 4802", "上課校區": " 第一校區", "部別": " 日間部四技", "科系": " 外語教育中心", "班級": " 外語四技一甲(第", "合班班級": " ", "永久課號": " 043C10240", "科目名稱": " 英文簡報", "學分": " 2.0", "授課時數": " 2.0", "實習時數": " 0", "必/選": " 選修", "授課教師": " 戴瑋", "教室": " E012", "修課人數": " 10", "人數上限": " 25", "上課時間": " (四)5-6", "全英語授課": " 是", "遠距教學": " 否", "授課大綱": "授課大綱", "備註": " 限非應英系學生修讀，107學年度後入學生通過英語免修計入外語畢業學分。"}, {"選課代號": " 4803", "上課校區": " 第一校區", "部別": " 日間部四技", "科系": " 外語教育中心", "班級": " 外語四技一甲(第", "合班班級": " ", "永久課號": " 043C10044", "科目名稱": " 泰語(二)", "學分": " 2.0", "授課時數": " 2.0", "實習時數": " 0", "必/選": " 選修", "授課教師": " 李敏玉", "教室": " D106", "修課人數": " 28", "人數上限": " 40", "上課時間": " (五)1-2", "全英語授課": " 否", "遠距教學": " 否", "授課大綱": "授課大綱", "備註": " 107學年度後入學生通過英語免修計入外語畢業學分。"}, {"選課代號": " 4804", "上課校區": " 第一校區", "部別": " 日間部四技", "科系": " 外語教育中心", "班級": " 外語四技一甲(第", "合班班級": " ", "永久課號": " 043C10044", "科目名稱": " 泰語(二)", "學分": " 2.0", "授課時數": " 2.0", "實習時數": " 0", "必/選": " 選修", "授課教師": " 李敏玉", "教室": " D106", "修課人數": " 24", "人數上限": " 40", "上課時間": " (五)3-4", "全英語授課": " 否", "遠距教學": " 否", "授課大綱": "授課大綱", "備註": " 107學年度後入學生通過英語免修計入外語畢業學分。"}, {"選課代號": " 4805", "上課校區": " 第一校區", "部別": " 日間部四技", "科系": " 外語教育中心", "班級": " 外語四技一甲(第", "合班班級": " ", "永久課號": " 043C10044", "科目名稱": " 泰語(二)", "學分": " 2.0", "授課時數": " 2.0", "實習時數": " 0", "必/選": " 選修", "授課教師": " 潘婉玲", "教室": " E421", "修課人數": " 17", "人數上限": " 40", "上課時間": " (一)3-4", "全英語授課": " 否", "遠距教學": " 否", "授課大綱": "授課大綱", "備註": " 107學年度後入學生通過英語免修計入外語畢業學分。"}, {"選課代號": " 4807", "上課校區": " 第一校區", "部別": " 日間部四技", "科系": " 外語教育中心", "班級": " 外語四技一甲(第", "合班班級": " ", "永久課號": " 043C10027", "科目名稱": " 泰語(四)", "學分": " 2.0", "授課時數": " 2.0", "實習時數": " 0", "必/選": " 選修", "授課教師": " 潘婉玲", "教室": " E421", "修課人數": " 5", "人數上限": " 40", "上課時間": " (一)1-2", "全英語授課": " 否", "遠距教學": " 否", "授課大綱": "授課大綱", "備註": " 107學年度後入學生通過英語免修計入外語畢業學分。"}, {"選課代號": " 4808", "上課校區": " 第一校區", "部別": " 日間部四技", "科系": " 外語教育中心", "班級": " 外語四技一甲(第", "合班班級": " ", "永久課號": " 043C10068", "科目名稱": " 華語(一)", "學分": " 2.0", "授課時數": " 2.0", "實習時數": " 0", "必/選": " 選修", "授課教師": " 葉亭妤", "教室": " E424", "修課人數": " 3", "人數上限": " 30", "上課時間": " (五)3-4", "全英語授課": " 否", "遠距教學": " 否", "授課大綱": "授課大綱", "備註": " 限國際學生修讀"}, {"選課代號": " 4811", "上課校區": " 第一校區", "部別": " 日間部四技", "科系": " 外語教育中心", "班級": " 外語四技一甲(第", "合班班級": " ", "永久課號": " 043C10113", "科目名稱": " 華語(二)", "學分": " 2.0", "授課時數": " 2.0", "實習時數": " 0", "必/選": " 選修", "授課教師": " 雷雅安", "教室": " E416", "修課人數": " 4", "人數上限": " 30", "上課時間": " (五)3-4", "全英語授課": " 否", "遠距教學": " 否", "授課大綱": "授課大綱", "備註": " 限國際學生修讀"}, {"選課代號": " 4812", "上課校區": " 第一校區", "部別": " 日間部四技", "科系": " 外語教育中心", "班級": " 外語四技一甲(第", "合班班級": " ", "永久課號": " 043C10066", "科目名稱": " 華語(四)", "學分": " 2.0", "授課時數": " 2.0", "實習時數": " 0", "必/選": " 選修", "授課教師": " 雷雅安", "教室": " E416", "修課人數": " 7", "人數上限": " 30", "上課時間": " (一)7-8", "全英語授課": " 否", "遠距教學": " 否", "授課大綱": "授課大綱", "備註": " 限國際學生修讀"}, {"選課代號": " 4813", "上課校區": " 第一校區", "部別": " 日間部四技", "科系": " 外語教育中心", "班級": " 外語四技一甲(第", "合班班級": " ", "永久課號": " 043C10061", "科目名稱": " 商用英語", "學分": " 2.0", "授課時數": " 2.0", "實習時數": " 0", "必/選": " 選修", "授課教師": " 高玉珮", "教室": " E012", "修課人數": " 25", "人數上限": " 25", "上課時間": " (五)5-6", "全英語授課": " 是", "遠距教學": " 否", "授課大綱": "授課大綱", "備註": " 限非應英系學生修讀，107學年度後入學生通過英語免修計入外語畢業學分。"}, {"選課代號": " 4816", "上課校區": " 第一校區", "部別": " 日間部四技", "科系": " 外語教育中心", "班級": " 外語四技一甲(第", "合班班級": " ", "永久課號": " 043C10120", "科目名稱": " 越南語(二)", "學分": " 2.0", "授課時數": " 2.0", "實習時數": " 0", "必/選": " 選修", "授課教師": " 阮氏青河", "教室": " D105", "修課人數": " 11", "人數上限": " 40", "上課時間": " (五)1-2", "全英語授課": " 否", "遠距教學": " 否", "授課大綱": "授課大綱", "備註": " 107學年度後入學生通過英語免修計入外語畢業學分。"}, {"選課代號": " 4817", "上課校區": " 第一校區", "部別": " 日間部四技", "科系": " 外語教育中心", "班級": " 外語四技一甲(第", "合班班級": " ", "永久課號": " 043C10120", "科目名稱": " 越南語(二)", "學分": " 2.0", "授課時數": " 2.0", "實習時數": " 0", "必/選": " 選修", "授課教師": " 阮氏青河", "教室": " E304", "修課人數": " 6", "人數上限": " 40", "上課時間": " (一)5-6", "全英語授課": " 否", "遠距教學": " 否", "授課大綱": "授課大綱", "備註": " 107學年度後入學生通過英語免修計入外語畢業學分。"}, {"選課代號": " 4818", "上課校區": " 第一校區", "部別": " 日間部四技", "科系": " 外語教育中心", "班級": " 外語四技一甲(第", "合班班級": " ", "永久課號": " 043C10111", "科目名稱": " 越南語(四)", "學分": " 2.0", "授課時數": " 2.0", "實習時數": " 0", "必/選": " 選修", "授課教師": " 阮氏青河", "教室": " D105", "修課人數": " 9", "人數上限": " 40", "上課時間": " (五)3-4", "全英語授課": " 否", "遠距教學": " 否", "授課大綱": "授課大綱", "備註": " 107學年度後入學生通過英語免修計入外語畢業學分。"}, {"選課代號": " 4820", "上課校區": " 第一校區", "部別": " 日間部四技", "科系": " 外語教育中心", "班級": " 外語四技一甲(第", "合班班級": " ", "永久課號": " 043C10108", "科目名稱": " 國際議題英語討論", "學分": " 2.0", "授課時數": " 2.0", "實習時數": " 0", "必/選": " 選修", "授課教師": " 鄭凱睿", "教室": " E014", "修課人數": " 25", "人數上限": " 25", "上課時間": " (一)5-6", "全英語授課": " 是", "遠距教學": " 否", "授課大綱": "授課大綱", "備註": " 限非應英系學生修讀，107學年度後入學生通過英語免修計入外語畢業學分。"}, {"選課代號": " 4821", "上課校區": " 第一校區", "部別": " 日間部四技", "科系": " 外語教育中心", "班級": " 外語四技一甲(第", "合班班級": " ", "永久課號": " 043C10078", "科目名稱": " 跨文化主題-流行文化", "學分": " 2.0", "授課時數": " 2.0", "實習時數": " 0", "必/選": " 選修", "授課教師": " 戴瑋", "教室": " E012", "修課人數": " 17", "人數上限": " 25", "上課時間": " (二)5-6", "全英語授課": " 是", "遠距教學": " 否", "授課大綱": "授課大綱", "備註": " 限非應英系學生修讀，107學年度後入學生通過英語免修計入外語畢業學分。"}, {"選課代號": " 4822", "上課校區": " 第一校區", "部別": " 日間部四技", "科系": " 外語教育中心", "班級": " 外語四技一甲(第", "合班班級": " ", "永久課號": " 043C10110", "科目名稱": " 跨文化主題-科技與生活", "學分": " 2.0", "授課時數": " 2.0", "實習時數": " 0", "必/選": " 選修", "授課教師": " 柯偉丞", "教室": " E210", "修課人數": " 20", "人數上限": " 25", "上課時間": " (一)3-4", "全英語授課": " 是", "遠距教學": " 否", "授課大綱": "授課大綱", "備註": " 限非應英系學生修讀，107學年度後入學生通過英語免修計入外語畢業學分。"}, {"選課代號": " 4929", "上課校區": " 第一校區", "部別": " 日間部四技", "科系": " 外語教育中心", "班級": " 外語四技二甲(第", "合班班級": " ", "永久課號": " 043C00003", "科目名稱": " 實用英文(四)", "學分": " 2.0", "授課時數": " 2.0", "實習時數": " 0", "必/選": " 必修", "授課教師": " 吳昌恂", "教室": " E204", "修課人數": " 37", "人數上限": " 0", "上課時間": " (一)5-6", "全英語授課": " 否", "遠距教學": " 否", "授課大綱": "授課大綱", "備註": " 不開放選課：由外語中心依級數分班【限工.電資院選修：初-1】"}, {"選課代號": " 4930", "上課校區": " 第一校區", "部別": " 日間部四技", "科系": " 外語教育中心", "班級": " 外語四技二甲(第", "合班班級": " ", "永久課號": " 043C00003", "科目名稱": " 實用英文(四)", "學分": " 2.0", "授課時數": " 2.0", "實習時數": " 0", "必/選": " 必修", "授課教師": " 傅貞珍", "教室": " C204", "修課人數": " 39", "人數上限": " 0", "上課時間": " (一)7-8", "全英語授課": " 否", "遠距教學": " 否", "授課大綱": "授課大綱", "備註": " 不開放選課：由外語中心依級數分班【限工.電資院選修：初-2】"}, {"選課代號": " 4931", "上課校區": " 第一校區", "部別": " 日間部四技", "科系": " 外語教育中心", "班級": " 外語四技二甲(第", "合班班級": " ", "永久課號": " 043C00003", "科目名稱": " 實用英文(四)", "學分": " 2.0", "授課時數": " 2.0", "實習時數": " 0", "必/選": " 必修", "授課教師": " 黃尚文", "教室": " E016", "修課人數": " 30", "人數上限": " 0", "上課時間": " (一)5-6", "全英語授課": " 否", "遠距教學": " 否", "授課大綱": "授課大綱", "備註": " 不開放選課：由外語中心依級數分班【限工.電資院選修：中-3】"}, {"選課代號": " 4932", "上課校區": " 第一校區", "部別": " 日間部四技", "科系": " 外語教育中心", "班級": " 外語四技二甲(第", "合班班級": " ", "永久課號": " 043C00003", "科目名稱": " 實用英文(四)", "學分": " 2.0", "授課時數": " 2.0", "實習時數": " 0", "必/選": " 必修", "授課教師": " 戴瑋", "教室": " E010", "修課人數": " 30", "人數上限": " 0", "上課時間": " (一)5-6", "全英語授課": " 否", "遠距教學": " 否", "授課大綱": "授課大綱", "備註": " 不開放選課：由外語中心依級數分班【限工.電資院選修：中-4】"}, {"選課代號": " 4933", "上課校區": " 第一校區", "部別": " 日間部四技", "科系": " 外語教育中心", "班級": " 外語四技二甲(第", "合班班級": " ", "永久課號": " 043C00003", "科目名稱": " 實用英文(四)", "學分": " 2.0", "授課時數": " 2.0", "實習時數": " 0", "必/選": " 必修", "授課教師": " 莊心瑜", "教室": " E422", "修課人數": " 28", "人數上限": " 0", "上課時間": "  (一)5-6", "全英語授課": " 否", "遠距教學": " 否", "授課大綱": "授課大綱", "備註": " 不開放選課：由外語中心依級數分班【限工.電資院選修：中-5】"}, {"選課代號": " 4934", "上課校區": " 第一校區", "部別": " 日間部四技", "科系": " 外語教育中心", "班級": " 外語四技二甲(第", "合班班級": " ", "永久課號": " 043C00003", "科目名稱": " 實用英文(四)", "學分": " 2.0", "授課時數": " 2.0", "實習時數": " 0", "必/選": " 必修", "授課教師": " 柯偉丞", "教室": " E210", "修課人數": " 30", "人數上限": " 0", "上課時間": " (一)5-6", "全英語授課": " 否", "遠距教學": " 否", "授課大綱": "授課大綱", "備註": " 不開放選課：由外語中心依級數分班【限工.電資院選修：中-6】"}, {"選課代號": " 4935", "上課校區": " 第一校區", "部別": " 日間部四技", "科系": " 外語教育中心", "班級": " 外語四技二甲(第", "合班班級": " ", "永久課號": " 043C00003", "科目名稱": " 實用英文(四)", "學分": " 2.0", "授課時數": " 2.0", "實習時數": " 0", "必/選": " 必修", "授課教師": " 唐淑芳", "教室": " E403", "修課人數": " 32", "人數上限": " 0", "上課時間": " (一)5-6", "全英語授課": " 否", "遠距教學": " 否", "授課大綱": "授課大綱", "備註": " 不開放選課：由外語中心依級數分班【限工.電資院選修：中-7】"}, {"選課代號": " 4936", "上課校區": " 第一校區", "部別": " 日間部四技", "科系": " 外語教育中心", "班級": " 外語四技二甲(第", "合班班級": " ", "永久課號": " 043C00003", "科目名稱": " 實用英文(四)", "學分": " 2.0", "授課時數": " 2.0", "實習時數": " 0", "必/選": " 必修", "授課教師": " 黃尚文", "教室": " E016", "修課人數": " 28", "人數上限": " 0", "上課時間": " (一)7-8", "全英語授課": " 否", "遠距教學": " 否", "授課大綱": "授課大綱", "備註": " 不開放選課：由外語中心依級數分班【限工.電資院選修：中-8】"}, {"選課代號": " 4937", "上課校區": " 第一校區", "部別": " 日間部四技", "科系": " 外語教育中心", "班級": " 外語四技二甲(第", "合班班級": " ", "永久課號": " 043C00003", "科目名稱": " 實用英文(四)", "學分": " 2.0", "授課時數": " 2.0", "實習時數": " 0", "必/選": " 必修", "授課教師": " 黃海深", "教室": " E010", "修課人數": " 28", "人數上限": " 0", "上課時間": " (一)7-8", "全英語授課": " 否", "遠距教學": " 否", "授課大綱": "授課大綱", "備註": " 不開放選課：由外語中心依級數分班【限工.電資院選修：中-9】"}, {"選課代號": " 4938", "上課校區": " 第一校區", "部別": " 日間部四技", "科系": " 外語教育中心", "班級": " 外語四技二甲(第", "合班班級": " ", "永久課號": " 043C00003", "科目名稱": " 實用英文(四)", "學分": " 2.0", "授課時數": " 2.0", "實習時數": " 0", "必/選": " 必修", "授課教師": " 莊心瑜", "教室": " E422", "修課人數": " 29", "人數上限": " 0", "上課時間": "  (一)7-8", "全英語授課": " 否", "遠距教學": " 否", "授課大綱": "授課大綱", "備註": " 不開放選課：由外語中心依級數分班【限工.電資院選修：中-10】"}, {"選課代號": " 4939", "上課校區": " 第一校區", "部別": " 日間部四技", "科系": " 外語教育中心", "班級": " 外語四技二甲(第", "合班班級": " ", "永久課號": " 043C00003", "科目名稱": " 實用英文(四)", "學分": " 2.0", "授課時數": " 2.0", "實習時數": " 0", "必/選": " 必修", "授課教師": " 柯偉丞", "教室": " E210", "修課人數": " 29", "人數上限": " 0", "上課時間": " (一)7-8", "全英語授課": " 否", "遠距教學": " 否", "授課大綱": "授課大綱", "備註": " 不開放選課：由外語中心依級數分班【限工.電資院選修：中-11】"}, {"選課代號": " 4940", "上課校區": " 第一校區", "部別": " 日間部四技", "科系": " 外語教育中心", "班級": " 外語四技二甲(第", "合班班級": " ", "永久課號": " 043C00003", "科目名稱": " 實用英文(四)", "學分": " 2.0", "授課時數": " 2.0", "實習時數": " 0", "必/選": " 必修", "授課教師": " 鄭凱睿", "教室": " E014", "修課人數": " 30", "人數上限": " 0", "上課時間": " (一)7-8", "全英語授課": " 否", "遠距教學": " 否", "授課大綱": "授課大綱", "備註": " 不開放選課：由外語中心依級數分班【限工.電資院選修：中-12】"}, {"選課代號": " 4941", "上課校區": " 第一校區", "部別": " 日間部四技", "科系": " 外語教育中心", "班級": " 外語四技二甲(第", "合班班級": " ", "永久課號": " 043C00003", "科目名稱": " 實用英文(四)", "學分": " 2.0", "授課時數": " 2.0", "實習時數": " 0", "必/選": " 必修", "授課教師": " 許呈瑟", "教室": " E203", "修課人數": " 31", "人數上限": " 0", "上課時間": " (一)5-6", "全英語授課": " 否", "遠距教學": " 否", "授課大綱": "授課大綱", "備註": " 不開放選課：由外語中心依級數分班【限工.電資院選修：高-13】"}, {"選課代號": " 4942", "上課校區": " 第一校區", "部別": " 日間部四技", "科系": " 外語教育中心", "班級": " 外語四技二甲(第", "合班班級": " ", "永久課號": " 043C00003", "科目名稱": " 實用英文(四)", "學分": " 2.0", "授課時數": " 2.0", "實習時數": " 0", "必/選": " 必修", "授課教師": " 林汝穗", "教室": " E002", "修課人數": " 32", "人數上限": " 0", "上課時間": " (一)5-6", "全英語授課": " 否", "遠距教學": " 否", "授課大綱": "授課大綱", "備註": " 不開放選課：由外語中心依級數分班【限工.電資院選修：高-14】"}, {"選課代號": " 4943", "上課校區": " 第一校區", "部別": " 日間部四技", "科系": " 外語教育中心", "班級": " 外語四技二甲(第", "合班班級": " ", "永久課號": " 043C00003", "科目名稱": " 實用英文(四)", "學分": " 2.0", "授課時數": " 2.0", "實習時數": " 0", "必/選": " 必修", "授課教師": " 施泊琹", "教室": " E213", "修課人數": " 29", "人數上限": " 0", "上課時間": " (一)5-6", "全英語授課": " 否", "遠距教學": " 否", "授課大綱": "授課大綱", "備註": " 不開放選課：由外語中心依級數分班【限工.電資院選修：高-15】"}, {"選課代號": " 4944", "上課校區": " 第一校區", "部別": " 日間部四技", "科系": " 外語教育中心", "班級": " 外語四技二甲(第", "合班班級": " ", "永久課號": " 043C00003", "科目名稱": " 實用英文(四)", "學分": " 2.0", "授課時數": " 2.0", "實習時數": " 0", "必/選": " 必修", "授課教師": " 范嘉玲", "教室": " E209", "修課人數": " 34", "人數上限": " 0", "上課時間": " (一)5-6", "全英語授課": " 否", "遠距教學": " 否", "授課大綱": "授課大綱", "備註": " 不開放選課：由外語中心依級數分班【限工.電資院選修：高-16】"}, {"選課代號": " 4945", "上課校區": " 第一校區", "部別": " 日間部四技", "科系": " 外語教育中心", "班級": " 外語四技二甲(第", "合班班級": " ", "永久課號": " 043C00003", "科目名稱": " 實用英文(四)", "學分": " 2.0", "授課時數": " 2.0", "實習時數": " 0", "必/選": " 必修", "授課教師": " 范嘉玲", "教室": " E209", "修課人數": " 30", "人數上限": " 0", "上課時間": " (一)7-8", "全英語授課": " 否", "遠距教學": " 否", "授課大綱": "授課大綱", "備註": " 不開放選課：由外語中心依級數分班【限工.電資院選修：高-17】"}, {"選課代號": " 4946", "上課校區": " 第一校區", "部別": " 日間部四技", "科系": " 外語教育中心", "班級": " 外語四技二甲(第", "合班班級": " ", "永久課號": " 043C00003", "科目名稱": " 實用英文(四)", "學分": " 2.0", "授課時數": " 2.0", "實習時數": " 0", "必/選": " 必修", "授課教師": " 許呈瑟", "教室": " E203", "修課人數": " 27", "人數上限": " 0", "上課時間": " (一)7-8", "全英語授課": " 否", "遠距教學": " 否", "授課大綱": "授課大綱", "備註": " 不開放選課：由外語中心依級數分班【限工.電資院選修：高-18】"}, {"選課代號": " 4947", "上課校區": " 第一校區", "部別": " 日間部四技", "科系": " 外語教育中心", "班級": " 外語四技二甲(第", "合班班級": " ", "永久課號": " 043C00003", "科目名稱": " 實用英文(四)", "學分": " 2.0", "授課時數": " 2.0", "實習時數": " 0", "必/選": " 必修", "授課教師": " 林汝穗", "教室": " E002", "修課人數": " 29", "人數上限": " 0", "上課時間": " (一)7-8", "全英語授課": " 否", "遠距教學": " 否", "授課大綱": "授課大綱", "備註": " 不開放選課：由外語中心依級數分班【限工.電資院選修：高-19】"}, {"選課代號": " 4948", "上課校區": " 第一校區", "部別": " 日間部四技", "科系": " 外語教育中心", "班級": " 外語四技二甲(第", "合班班級": " ", "永久課號": " 043C00003", "科目名稱": " 實用英文(四)", "學分": " 2.0", "授課時數": " 2.0", "實習時數": " 0", "必/選": " 必修", "授課教師": " 吳昌恂", "教室": " J124", "修課人數": " 21", "人數上限": " 0", "上課時間": " (五)3-4", "全英語授課": " 否", "遠距教學": " 否", "授課大綱": "授課大綱", "備註": " 不開放選課：由外語中心依級數分班【限外.財.管院選修：初-20】"}, {"選課代號": " 4949", "上課校區": " 第一校區", "部別": " 日間部四技", "科系": " 外語教育中心", "班級": " 外語四技二甲(第", "合班班級": " ", "永久課號": " 043C00003", "科目名稱": " 實用英文(四)", "學分": " 2.0", "授課時數": " 2.0", "實習時數": " 0", "必/選": " 必修", "授課教師": " 唐淑芳", "教室": " E212", "修課人數": " 30", "人數上限": " 0", "上課時間": " (五)1-2", "全英語授課": " 否", "遠距教學": " 否", "授課大綱": "授課大綱", "備註": " 不開放選課：由外語中心依級數分班【限外.財.管院選修：中-21】"}, {"選課代號": " 4950", "上課校區": " 第一校區", "部別": " 日間部四技", "科系": " 外語教育中心", "班級": " 外語四技二甲(第", "合班班級": " ", "永久課號": " 043C00003", "科目名稱": " 實用英文(四)", "學分": " 2.0", "授課時數": " 2.0", "實習時數": " 0", "必/選": " 必修", "授課教師": " 張晴", "教室": " E421", "修課人數": " 31", "人數上限": " 0", "上課時間": " (五)1-2", "全英語授課": " 否", "遠距教學": " 否", "授課大綱": "授課大綱", "備註": " 不開放選課：由外語中心依級數分班【限外.財.管院選修：中-22】"}, {"選課代號": " 4951", "上課校區": " 第一校區", "部別": " 日間部四技", "科系": " 外語教育中心", "班級": " 外語四技二甲(第", "合班班級": " ", "永久課號": " 043C00003", "科目名稱": " 實用英文(四)", "學分": " 2.0", "授課時數": " 2.0", "實習時數": " 0", "必/選": " 必修", "授課教師": " 鄧安妮", "教室": " E301", "修課人數": " 31", "人數上限": " 0", "上課時間": " (五)1-2", "全英語授課": " 否", "遠距教學": " 否", "授課大綱": "授課大綱", "備註": " 不開放選課：由外語中心依級數分班【限外.財.管院選修：中-23】"}, {"選課代號": " 4952", "上課校區": " 第一校區", "部別": " 日間部四技", "科系": " 外語教育中心", "班級": " 外語四技二甲(第", "合班班級": " ", "永久課號": " 043C00003", "科目名稱": " 實用英文(四)", "學分": " 2.0", "授課時數": " 2.0", "實習時數": " 0", "必/選": " 必修", "授課教師": " 吳昌恂", "教室": " J124", "修課人數": " 31", "人數上限": " 0", "上課時間": " (五)1-2", "全英語授課": " 否", "遠距教學": " 否", "授課大綱": "授課大綱", "備註": " 不開放選課：由外語中心依級數分班【限外.財.管院選修：中-24】"}, {"選課代號": " 4953", "上課校區": " 第一校區", "部別": " 日間部四技", "科系": " 外語教育中心", "班級": " 外語四技二甲(第", "合班班級": " ", "永久課號": " 043C00003", "科目名稱": " 實用英文(四)", "學分": " 2.0", "授課時數": " 2.0", "實習時數": " 0", "必/選": " 必修", "授課教師": " 鄧安妮", "教室": " E301", "修課人數": " 34", "人數上限": " 0", "上課時間": " (五)3-4", "全英語授課": " 否", "遠距教學": " 否", "授課大綱": "授課大綱", "備註": " 不開放選課：由外語中心依級數分班【限外.財.管院選修：中-25】"}, {"選課代號": " 4954", "上課校區": " 第一校區", "部別": " 日間部四技", "科系": " 外語教育中心", "班級": " 外語四技二甲(第", "合班班級": " ", "永久課號": " 043C00003", "科目名稱": " 實用英文(四)", "學分": " 2.0", "授課時數": " 2.0", "實習時數": " 0", "必/選": " 必修", "授課教師": " 唐淑芳", "教室": " E213", "修課人數": " 34", "人數上限": " 0", "上課時間": " (五)3-4", "全英語授課": " 否", "遠距教學": " 否", "授課大綱": "授課大綱", "備註": " 不開放選課：由外語中心依級數分班【限外.財.管院選修：中-26】"}, {"選課代號": " 4955", "上課校區": " 第一校區", "部別": " 日間部四技", "科系": " 外語教育中心", "班級": " 外語四技二甲(第", "合班班級": " ", "永久課號": " 043C00003", "科目名稱": " 實用英文(四)", "學分": " 2.0", "授課時數": " 2.0", "實習時數": " 0", "必/選": " 必修", "授課教師": " 張晴", "教室": " E421", "修課人數": " 33", "人數上限": " 0", "上課時間": " (五)3-4", "全英語授課": " 否", "遠距教學": " 否", "授課大綱": "授課大綱", "備註": " 不開放選課：由外語中心依級數分班【限外.財.管院選修：中-27】"}, {"選課代號": " 4956", "上課校區": " 第一校區", "部別": " 日間部四技", "科系": " 外語教育中心", "班級": " 外語四技二甲(第", "合班班級": " ", "永久課號": " 043C00003", "科目名稱": " 實用英文(四)", "學分": " 2.0", "授課時數": " 2.0", "實習時數": " 0", "必/選": " 必修", "授課教師": " 張淑君", "教室": " E115", "修課人數": " 31", "人數上限": " 0", "上課時間": " (五)3-4", "全英語授課": " 否", "遠距教學": " 否", "授課大綱": "授課大綱", "備註": " 不開放選課：由外語中心依級數分班【限外.財.管院選修：中-28】"}, {"選課代號": " 4957", "上課校區": " 第一校區", "部別": " 日間部四技", "科系": " 外語教育中心", "班級": " 外語四技二甲(第", "合班班級": " ", "永久課號": " 043C00003", "科目名稱": " 實用英文(四)", "學分": " 2.0", "授課時數": " 2.0", "實習時數": " 0", "必/選": " 必修", "授課教師": " 陳佳艷", "教室": " E214", "修課人數": " 28", "人數上限": " 0", "上課時間": " (五)1-2", "全英語授課": " 否", "遠距教學": " 否", "授課大綱": "授課大綱", "備註": " 不開放選課：由外語中心依級數分班【限外.財.管院選修：高-29】"}, {"選課代號": " 4958", "上課校區": " 第一校區", "部別": " 日間部四技", "科系": " 外語教育中心", "班級": " 外語四技二甲(第", "合班班級": " ", "永久課號": " 043C00003", "科目名稱": " 實用英文(四)", "學分": " 2.0", "授課時數": " 2.0", "實習時數": " 0", "必/選": " 必修", "授課教師": " 邱翊婷", "教室": " E003", "修課人數": " 30", "人數上限": " 0", "上課時間": " (五)1-2", "全英語授課": " 否", "遠距教學": " 否", "授課大綱": "授課大綱", "備註": " 不開放選課：由外語中心依級數分班【限外.財.管院選修：高-30】"}, {"選課代號": " 4959", "上課校區": " 第一校區", "部別": " 日間部四技", "科系": " 外語教育中心", "班級": " 外語四技二甲(第", "合班班級": " ", "永久課號": " 043C00003", "科目名稱": " 實用英文(四)", "學分": " 2.0", "授課時數": " 2.0", "實習時數": " 0", "必/選": " 必修", "授課教師": " 安慧芝", "教室": " E307", "修課人數": " 29", "人數上限": " 0", "上課時間": "  (五)1-2", "全英語授課": " 否", "遠距教學": " 否", "授課大綱": "授課大綱", "備註": " 不開放選課：由外語中心依級數分班【限外.財.管院選修：高-31】"}, {"選課代號": " 4960", "上課校區": " 第一校區", "部別": " 日間部四技", "科系": " 外語教育中心", "班級": " 外語四技二甲(第", "合班班級": " ", "永久課號": " 043C00003", "科目名稱": " 實用英文(四)", "學分": " 2.0", "授課時數": " 2.0", "實習時數": " 0", "必/選": " 必修", "授課教師": " 趙秀玲", "教室": " E306", "修課人數": " 30", "人數上限": " 0", "上課時間": " (五)1-2", "全英語授課": " 否", "遠距教學": " 否", "授課大綱": "授課大綱", "備註": " 不開放選課：由外語中心依級數分班【限外.財.管院選修：高-32】"}, {"選課代號": " 4961", "上課校區": " 第一校區", "部別": " 日間部四技", "科系": " 外語教育中心", "班級": " 外語四技二甲(第", "合班班級": " ", "永久課號": " 043C00003", "科目名稱": " 實用英文(四)", "學分": " 2.0", "授課時數": " 2.0", "實習時數": " 0", "必/選": " 必修", "授課教師": " 林耕安", "教室": " E209", "修課人數": " 30", "人數上限": " 0", "上課時間": " (五)1-2", "全英語授課": " 否", "遠距教學": " 否", "授課大綱": "授課大綱", "備註": " 不開放選課：由外語中心依級數分班【限外.財.管院選修：高-33】"}, {"選課代號": " 4962", "上課校區": " 第一校區", "部別": " 日間部四技", "科系": " 外語教育中心", "班級": " 外語四技二甲(第", "合班班級": " ", "永久課號": " 043C00003", "科目名稱": " 實用英文(四)", "學分": " 2.0", "授課時數": " 2.0", "實習時數": " 0", "必/選": " 必修", "授課教師": " 黃尚文", "教室": " E115", "修課人數": " 28", "人數上限": " 0", "上課時間": " (五)1-2", "全英語授課": " 否", "遠距教學": " 否", "授課大綱": "授課大綱", "備註": " 不開放選課：由外語中心依級數分班【限外.財.管院選修：高-34】"}, {"選課代號": " 4963", "上課校區": " 第一校區", "部別": " 日間部四技", "科系": " 外語教育中心", "班級": " 外語四技二甲(第", "合班班級": " ", "永久課號": " 043C00003", "科目名稱": " 實用英文(四)", "學分": " 2.0", "授課時數": " 2.0", "實習時數": " 0", "必/選": " 必修", "授課教師": " 胡智翔", "教室": " E109", "修課人數": " 28", "人數上限": " 0", "上課時間": " (五)3-4", "全英語授課": " 否", "遠距教學": " 否", "授課大綱": "授課大綱", "備註": " 不開放選課：由外語中心依級數分班【限外.財.管院選修：高-35】"}, {"選課代號": " 4964", "上課校區": " 第一校區", "部別": " 日間部四技", "科系": " 外語教育中心", "班級": " 外語四技二甲(第", "合班班級": " ", "永久課號": " 043C00003", "科目名稱": " 實用英文(四)", "學分": " 2.0", "授課時數": " 2.0", "實習時數": " 0", "必/選": " 必修", "授課教師": " 陳佳艷", "教室": " E214", "修課人數": " 30", "人數上限": " 0", "上課時間": " (五)3-4", "全英語授課": " 否", "遠距教學": " 否", "授課大綱": "授課大綱", "備註": " 不開放選課：由外語中心依級數分班【限外.財.管院選修：高-36】"}, {"選課代號": " 4965", "上課校區": " 第一校區", "部別": " 日間部四技", "科系": " 外語教育中心", "班級": " 外語四技二甲(第", "合班班級": " ", "永久課號": " 043C00003", "科目名稱": " 實用英文(四)", "學分": " 2.0", "授課時數": " 2.0", "實習時數": " 0", "必/選": " 必修", "授課教師": " 賴偉毅", "教室": " E110", "修課人數": " 30", "人數上限": " 0", "上課時間": " (五)3-4", "全英語授課": " 否", "遠距教學": " 否", "授課大綱": "授課大綱", "備註": " 不開放選課：由外語中心依級數分班【限外.財.管院選修：高-37】"}, {"選課代號": " 4966", "上課校區": " 第一校區", "部別": " 日間部四技", "科系": " 外語教育中心", "班級": " 外語四技二甲(第", "合班班級": " ", "永久課號": " 043C00003", "科目名稱": " 實用英文(四)", "學分": " 2.0", "授課時數": " 2.0", "實習時數": " 0", "必/選": " 必修", "授課教師": " 羅麗卿", "教室": " E303", "修課人數": " 30", "人數上限": " 0", "上課時間": " (五)3-4", "全英語授課": " 否", "遠距教學": " 否", "授課大綱": "授課大綱", "備註": " 不開放選課：由外語中心依級數分班【限外.財.管院選修：高-38】"}, {"選課代號": " 4967", "上課校區": " 第一校區", "部別": " 日間部四技", "科系": " 外語教育中心", "班級": " 外語四技二甲(第", "合班班級": " ", "永久課號": " 043C00003", "科目名稱": " 實用英文(四)", "學分": " 2.0", "授課時數": " 2.0", "實習時數": " 0", "必/選": " 必修", "授課教師": " 邱翊婷", "教室": " E003", "修課人數": " 30", "人數上限": " 0", "上課時間": " (五)3-4", "全英語授課": " 否", "遠距教學": " 否", "授課大綱": "授課大綱", "備註": " 不開放選課：由外語中心依級數分班【限外.財.管院選修：高-39】"}, {"選課代號": " 4968", "上課校區": " 第一校區", "部別": " 日間部四技", "科系": " 外語教育中心", "班級": " 外語四技二甲(第", "合班班級": " ", "永久課號": " 043C00003", "科目名稱": " 實用英文(四)", "學分": " 2.0", "授課時數": " 2.0", "實習時數": " 0", "必/選": " 必修", "授課教師": " 鄭凱睿", "教室": " E212", "修課人數": " 29", "人數上限": " 0", "上課時間": " (五)3-4", "全英語授課": " 否", "遠距教學": " 否", "授課大綱": "授課大綱", "備註": " 不開放選課：由外語中心依級數分班【限外.財.管院選修：高-40】"}, {"選課代號": " 4969", "上課校區": " 第一校區", "部別": " 日間部四技", "科系": " 外語教育中心", "班級": " 外語四技二甲(第", "合班班級": " ", "永久課號": " 043C00003", "科目名稱": " 實用英文(四)", "學分": " 2.0", "授課時數": " 2.0", "實習時數": " 0", "必/選": " 必修", "授課教師": " 安慧芝", "教室": " E307", "修課人數": " 33", "人數上限": " 0", "上課時間": "  (五)3-4", "全英語授課": " 否", "遠距教學": " 否", "授課大綱": "授課大綱", "備註": " 不開放選課：由外語中心依級數分班【限外.財.管院選修：高-41】"}]